paracle-1.0.2.dist-info/licenses/LICENSE
paracle_a2a/__init__.py
paracle_a2a/config.py
paracle_a2a/exceptions.py
paracle_a2a/registry.py
paracle_a2a/utils.py
paracle_a2a/client/__init__.py
paracle_a2a/client/a2a_client.py
paracle_a2a/client/discovery.py
paracle_a2a/client/streaming.py
paracle_a2a/integration/__init__.py
paracle_a2a/integration/a2a_tool.py
paracle_a2a/integration/bridge.py
paracle_a2a/models/__init__.py
paracle_a2a/server/__init__.py
paracle_a2a/server/agent_card_generator.py
paracle_a2a/server/agent_executor.py
paracle_a2a/server/app.py
paracle_a2a/server/event_queue.py
paracle_a2a/server/task_manager.py
paracle_adapters/__init__.py
paracle_adapters/autogen_adapter.py
paracle_adapters/base.py
paracle_adapters/crewai_adapter.py
paracle_adapters/exceptions.py
paracle_adapters/langchain_adapter.py
paracle_adapters/llamaindex_adapter.py
paracle_adapters/msaf_adapter.py
paracle_adapters/py.typed
paracle_adapters/registry.py
paracle_agent_comm/__init__.py
paracle_agent_comm/engine.py
paracle_agent_comm/exceptions.py
paracle_agent_comm/models.py
paracle_agent_comm/bridges/__init__.py
paracle_agent_comm/bridges/a2a_bridge.py
paracle_agent_comm/patterns/__init__.py
paracle_agent_comm/patterns/broadcast.py
paracle_agent_comm/patterns/coordinator.py
paracle_agent_comm/patterns/peer_to_peer.py
paracle_agent_comm/persistence/__init__.py
paracle_agent_comm/persistence/session_store.py
paracle_agent_comm/persistence/sqlite_store.py
paracle_api/__init__.py
paracle_api/errors.py
paracle_api/main.py
paracle_api/py.typed
paracle_api/middleware/__init__.py
paracle_api/middleware/cache.py
paracle_api/routers/__init__.py
paracle_api/routers/agent_crud.py
paracle_api/routers/agents.py
paracle_api/routers/approvals.py
paracle_api/routers/auth.py
paracle_api/routers/health.py
paracle_api/routers/ide.py
paracle_api/routers/kanban.py
paracle_api/routers/logs.py
paracle_api/routers/observability.py
paracle_api/routers/parac.py
paracle_api/routers/reviews.py
paracle_api/routers/tool_crud.py
paracle-1.0.2.dist-info/METADATA
paracle-1.0.2.dist-info/WHEEL
paracle-1.0.2.dist-info/entry_points.txt
paracle-1.0.2.dist-info/top_level.txt
paracle-1.0.2.dist-info/RECORD
