Metadata-Version: 2.4
Name: paracle
Version: 1.0.2
Summary: User-driven multi-agent framework for AI-native applications
Author-email: IbIFACE-Team <dev@ibiface.com>, ANGX <dev@ibiface.com>
Maintainer-email: IbIFACE-Team <dev@ibiface.com>
License-Expression: Apache-2.0
Project-URL: Homepage, https://github.com/IbIFACE-Tech/paracle-lite
Project-URL: Documentation, https://paracle.readthedocs.io
Project-URL: Repository, https://github.com/IbIFACE-Tech/paracle-lite
Project-URL: Issues, https://github.com/IbIFACE-Tech/paracle-lite/issues
Project-URL: Changelog, https://github.com/IbIFACE-Tech/paracle-lite/blob/main/CHANGELOG.md
Project-URL: PyPI, https://pypi.org/project/paracle/
Keywords: ai,agents,multi-agent,llm,framework,orchestration,workflow
Classifier: Development Status :: 4 - Beta
Classifier: Intended Audience :: Developers
Classifier: Programming Language :: Python :: 3
Classifier: Programming Language :: Python :: 3.10
Classifier: Programming Language :: Python :: 3.11
Classifier: Programming Language :: Python :: 3.12
Classifier: Programming Language :: Python :: 3.13
Classifier: Programming Language :: Python :: 3.14
Classifier: Topic :: Software Development :: Libraries :: Application Frameworks
Classifier: Topic :: Scientific/Engineering :: Artificial Intelligence
Classifier: Typing :: Typed
Requires-Python: >=3.10
License-File: LICENSE
Requires-Dist: typing-extensions
Requires-Dist: pydantic>=2.5.0
Requires-Dist: pydantic-settings>=2.1.0
Requires-Dist: python-ulid>=2.2.0
Requires-Dist: click>=8.1.0
Requires-Dist: rich>=13.7.0
Requires-Dist: pyyaml>=6.0.1
Requires-Dist: httpx>=0.27.0
Requires-Dist: filelock>=3.13.0
Requires-Dist: watchdog>=3.0.0
Requires-Dist: asyncssh>=2.14.0
Requires-Dist: websockets>=12.0
Requires-Dist: bcrypt>=5.0.0
Requires-Dist: argon2-cffi>=25.1.0
Requires-Dist: python-multipart>=0.0.21
Requires-Dist: jinja2>=3.1.0
Requires-Dist: a2a-sdk>=0.3.0
Requires-Dist: anthropic>=0.75.0
Requires-Dist: sqlalchemy>=2.0.45
Provides-Extra: api
Requires-Dist: fastapi>=0.104.1; extra == "api"
Requires-Dist: uvicorn[standard]>=0.24.0; extra == "api"
Requires-Dist: python-jose[cryptography]>=3.3.0; extra == "api"
Requires-Dist: passlib[bcrypt]>=1.7.4; extra == "api"
Provides-Extra: store
Requires-Dist: sqlalchemy>=2.0.23; extra == "store"
Requires-Dist: alembic>=1.13.1; extra == "store"
Provides-Extra: events
Requires-Dist: redis>=5.0.1; extra == "events"
Provides-Extra: sandbox
Requires-Dist: docker>=7.0.0; extra == "sandbox"
Requires-Dist: psutil>=5.9.0; extra == "sandbox"
Provides-Extra: transport
Requires-Dist: asyncssh>=2.14.0; extra == "transport"
Requires-Dist: websockets>=12.0; extra == "transport"
Provides-Extra: meta
Requires-Dist: sqlalchemy>=2.0.23; extra == "meta"
Requires-Dist: aiosqlite>=0.19.0; extra == "meta"
Provides-Extra: postgres
Requires-Dist: asyncpg>=0.29.0; extra == "postgres"
Requires-Dist: psycopg2-binary>=2.9.9; extra == "postgres"
Requires-Dist: pgvector>=0.2.4; extra == "postgres"
Requires-Dist: sqlalchemy>=2.0.23; extra == "postgres"
Provides-Extra: meta-full
Requires-Dist: paracle[meta,postgres]; extra == "meta-full"
Provides-Extra: providers
Requires-Dist: openai>=1.3.7; extra == "providers"
Requires-Dist: anthropic>=0.7.8; extra == "providers"
Requires-Dist: cohere>=5.0.0; extra == "providers"
Provides-Extra: providers-extended
Requires-Dist: paracle[providers]; extra == "providers-extended"
Requires-Dist: google-genai>=0.1.0; extra == "providers-extended"
Requires-Dist: groq>=0.4.0; extra == "providers-extended"
Provides-Extra: azure
Requires-Dist: openai>=1.3.7; extra == "azure"
Requires-Dist: azure-identity>=1.15.0; extra == "azure"
Provides-Extra: aws
Requires-Dist: boto3>=1.34.0; extra == "aws"
Requires-Dist: botocore>=1.34.0; extra == "aws"
Provides-Extra: gcp
Requires-Dist: google-cloud-aiplatform>=1.38.0; extra == "gcp"
Requires-Dist: google-auth>=2.23.0; extra == "gcp"
Provides-Extra: cloud
Requires-Dist: paracle[aws,azure,gcp]; extra == "cloud"
Provides-Extra: langchain
Requires-Dist: langchain>=0.2.0; extra == "langchain"
Requires-Dist: langchain-core>=0.2.0; extra == "langchain"
Requires-Dist: langchain-openai>=0.1.0; extra == "langchain"
Requires-Dist: langgraph>=0.1.0; extra == "langchain"
Provides-Extra: llamaindex
Requires-Dist: llama-index>=0.10.0; extra == "llamaindex"
Requires-Dist: llama-index-llms-openai>=0.1.0; extra == "llamaindex"
Provides-Extra: crewai
Requires-Dist: crewai>=0.41.0; extra == "crewai"
Requires-Dist: crewai-tools>=0.4.0; extra == "crewai"
Provides-Extra: autogen
Requires-Dist: autogen-agentchat>=0.4.0; extra == "autogen"
Requires-Dist: autogen-ext>=0.4.0; extra == "autogen"
Provides-Extra: msaf
Requires-Dist: agent-framework>=0.1.0; extra == "msaf"
Provides-Extra: msaf-azure
Requires-Dist: azure-ai-projects>=1.0.0b3; extra == "msaf-azure"
Provides-Extra: adapters
Requires-Dist: paracle[autogen,crewai,langchain,llamaindex,msaf]; extra == "adapters"
Provides-Extra: observability
Requires-Dist: prometheus-client>=0.19.0; extra == "observability"
Requires-Dist: opentelemetry-api>=1.21.0; extra == "observability"
Provides-Extra: dev
Requires-Dist: pytest>=7.4.3; extra == "dev"
Requires-Dist: pytest-asyncio>=0.21.1; extra == "dev"
Requires-Dist: pytest-cov>=4.1.0; extra == "dev"
Requires-Dist: pytest-mock>=3.12.0; extra == "dev"
Requires-Dist: httpx>=0.27.0; extra == "dev"
Requires-Dist: black>=23.11.0; extra == "dev"
Requires-Dist: isort>=5.12.0; extra == "dev"
Requires-Dist: mypy>=1.7.1; extra == "dev"
Requires-Dist: ruff>=0.1.6; extra == "dev"
Requires-Dist: bandit>=1.7.5; extra == "dev"
Requires-Dist: safety>=2.3.0; extra == "dev"
Requires-Dist: pre-commit>=3.6.0; extra == "dev"
Requires-Dist: sqlalchemy>=2.0.23; extra == "dev"
Requires-Dist: alembic>=1.13.1; extra == "dev"
Provides-Extra: docs
Requires-Dist: mkdocs>=1.5.3; extra == "docs"
Requires-Dist: mkdocs-material>=9.4.14; extra == "docs"
Requires-Dist: mkdocstrings[python]>=0.24.0; extra == "docs"
Provides-Extra: all
Requires-Dist: paracle[adapters,api,cloud,events,observability,providers,sandbox,store]; extra == "all"
Dynamic: license-file
